highmath/__init__.py
highmath/mathdir/math_methods.py
highmath-0.0.3.dist-info/METADATA
highmath-0.0.3.dist-info/WHEEL
highmath-0.0.3.dist-info/licenses/LICENSE
highmath-0.0.3.dist-info/RECORD
